tarwiiga_basic/__init__.py
tarwiiga_basic/llm.py
tarwiiga_basic/adgen/__init__.py
tarwiiga_basic/adgen/generator.py
tarwiiga_basic/sitegen/__init__.py
tarwiiga_basic/sitegen/generator.py
tarwiiga_basic-1.0.0.dist-info/METADATA
tarwiiga_basic-1.0.0.dist-info/WHEEL
tarwiiga_basic-1.0.0.dist-info/RECORD
