Metadata-Version: 2.3
Name: tarwiiga_basic
Version: 1.0.0
Summary: Tarwiiga Python Package
Author-email: Tarwiiga <tarwiiga@gmail.com>
Requires-Python: >=3.11
Requires-Dist: langchain
Requires-Dist: langchain-google-genai
